<ibis>
	<adapter name="Archives" description="Archives" >

		<receiver
			className="nl.nn.adapterframework.receivers.GenericReceiver"
			name="Archives"
		>
			<listener 
				className="nl.nn.adapterframework.http.rest.ApiListener"
				uriPattern="archives"
				method="GET"
				produces="JSON"
			/>
		</receiver>
		
		<pipeline firstPipe="result">
		
			<exits>
				<exit path="OK" state="success" code="200"/>
				<exit path="NotModified" state="success" code="304" empty="true" />
				<exit path="BadRequest" state="error" code="400" empty="true" />
				<exit path="NotAuthorized" state="error" code="401" empty="true" />
				<exit path="NotAllowed" state="error" code="403" empty="true" />
				<exit path="ServerError" state="error" code="500" empty="true" />
			</exits>
			
			<pipe
				name="result"
				className="nl.nn.adapterframework.pipes.FixedResult"
				returnString='[{"itemTypeId":"$t!-2_DEP_008_02_03_00v-1","displayName":"Finance Registratie","localName":"DEP_008_02_03_00","queryName":"DEP_008_02_03_00"},{"itemTypeId":"$t!-2_DEP_008_02_02_00v-1","displayName":"Finance AP Facturen","localName":"DEP_008_02_02_00","queryName":"DEP_008_02_02_00"},{"itemTypeId":"$t!-2_DEP_008_02_06_00v-1","displayName":"Finance Registratie - Niet in gebruik","localName":"DEP_008_02_06_00","queryName":"DEP_008_02_06_00"},{"itemTypeId":"$t!-2_DEP_008_02_05_00v-1","displayName":"Finance AP Facturen - Niet in gebruik","localName":"DEP_008_02_05_00","queryName":"DEP_008_02_05_00"},{"itemTypeId":"$t!-2_DEP_006_09_01_00v-1","displayName":"AAV Z-VP Schade - Claims","localName":"DEP_006_09_01_00","queryName":"DEP_006_09_01_00"},{"itemTypeId":"$t!-2_DEP_006_09_00_00v-1","displayName":"AAV Z-VP Schade - Acc&amp;amp;Beheer","localName":"DEP_006_09_00_00","queryName":"DEP_006_09_00_00"},{"itemTypeId":"$t!-2_DEP_006_08_02_00v-1","displayName":"AAV Z-AAS - Claims Medisch","localName":"DEP_006_08_02_00","queryName":"DEP_006_08_02_00"},{"itemTypeId":"$t!-2_DEP_006_08_01_00v-1","displayName":"AAV Z-AAS - Claims Alg.","localName":"DEP_006_08_01_00","queryName":"DEP_006_08_01_00"},{"itemTypeId":"$t!-2_DEP_006_08_00_00v-1","displayName":"AAV Z-AAS - Acc&amp;Beheer","localName":"DEP_006_08_00_00","queryName":"DEP_006_08_00_00"},{"itemTypeId":"$t!-2_DEP_006_07_05_00v-1","displayName":"AAV P-VP Schade - Claims","localName":"DEP_006_07_05_00","queryName":"DEP_006_07_05_00"},{"itemTypeId":"$t!-2_DEP_006_07_04_00v-1","displayName":"AAV P-VP Schade - Acc&amp;Beheer","localName":"DEP_006_07_04_00","queryName":"DEP_006_07_04_00"},{"itemTypeId":"$t!-2_DEP_006_07_03_00v-1","displayName":"AAV P-VP Leven - Claims Medisch","localName":"DEP_006_07_03_00","queryName":"DEP_006_07_03_00"},{"itemTypeId":"$t!-2_DEP_006_07_02_00v-1","displayName":"AAV P-VP Leven - Claims Alg.","localName":"DEP_006_07_02_00","queryName":"DEP_006_07_02_00"},{"itemTypeId":"$t!-2_DEP_006_07_01_00v-1","displayName":"AAV P-VP Leven - Acc&amp;Beheer Medisch","localName":"DEP_006_07_01_00","queryName":"DEP_006_07_01_00"},{"itemTypeId":"$t!-2_DEP_006_07_00_00v-1","displayName":"AAV P-VP Leven - Acc&amp;Beheer","localName":"DEP_006_07_00_00","queryName":"DEP_006_07_00_00"},{"itemTypeId":"$t!-2_DEP_006_06_04_00v-1","displayName":"AAV P-AAS - Claims Uitv. verz. Medisch","localName":"DEP_006_06_04_00","queryName":"DEP_006_06_04_00"},{"itemTypeId":"$t!-2_DEP_006_06_03_00v-1","displayName":"AAV P-AAS - Claims Medisch","localName":"DEP_006_06_03_00","queryName":"DEP_006_06_03_00"},{"itemTypeId":"$t!-2_DEP_006_06_02_00v-1","displayName":"AAV P-AAS - Claims Alg.","localName":"DEP_006_06_02_00","queryName":"DEP_006_06_02_00"},{"itemTypeId":"$t!-2_DEP_006_06_01_00v-1","displayName":"AAV P-AAS - Acc. Medisch","localName":"DEP_006_06_01_00","queryName":"DEP_006_06_01_00"},{"itemTypeId":"$t!-2_DEP_006_06_00_00v-1","displayName":"AAV P-AAS - Acc&amp;Beheer","localName":"DEP_006_06_00_00","queryName":"DEP_006_06_00_00"},{"itemTypeId":"$t!-2_DEP_006_05_03_00v-1","displayName":"AAV P-AAL - Claims Medisch","localName":"DEP_006_05_03_00","queryName":"DEP_006_05_03_00"},{"itemTypeId":"$t!-2_DEP_006_05_02_00v-1","displayName":"AAV P-AAL - Claims Alg.","localName":"DEP_006_05_02_00","queryName":"DEP_006_05_02_00"},{"itemTypeId":"$t!-2_DEP_006_05_01_00v-1","displayName":"AAV P-AAL - Acc. Medisch","localName":"DEP_006_05_01_00","queryName":"DEP_006_05_01_00"},{"itemTypeId":"$t!-2_DEP_006_05_00_00v-1","displayName":"AAV P-AAL - Acc&amp;Beheer","localName":"DEP_006_05_00_00","queryName":"DEP_006_05_00_00"},{"itemTypeId":"$t!-2_DEP_006_04_02_00v-1","displayName":"AAV Z-Klantgegevens","localName":"DEP_006_04_02_00","queryName":"DEP_006_04_02_00"},{"itemTypeId":"$t!-2_DEP_006_04_01_00v-1","displayName":"AAV Z-3e mak. Schade-Claims","localName":"DEP_006_04_01_00","queryName":"DEP_006_04_01_00"},{"itemTypeId":"$t!-2_DEP_006_04_00_00v-1","displayName":"AAV Z-3e mak. Beheer","localName":"DEP_006_04_00_00","queryName":"DEP_006_04_00_00"},{"itemTypeId":"$t!-2_DEP_008_02_04_00v-1","displayName":"Finance Dagafschrift","localName":"DEP_008_02_04_00","queryName":"DEP_008_02_04_00"},{"itemTypeId":"$t!-2_DEP_008_02_01_00v-1","displayName":"Finance Services","localName":"DEP_008_02_01_00","queryName":"DEP_008_02_01_00"},{"itemTypeId":"$t!-2_DEP_002_10_01_00v-1","displayName":"LSC Letselschade","localName":"DEP_002_10_01_00","queryName":"DEP_002_10_01_00"},{"itemTypeId":"$t!-2_DEP_002_11_01_00v-1","displayName":"Rechtsbijstand Algemeen","localName":"DEP_002_11_01_00","queryName":"DEP_002_11_01_00"},{"itemTypeId":"$t!-2_DEP_009_01_01_00v-1","displayName":"FSB Contracten","localName":"DEP_009_01_01_00","queryName":"DEP_009_01_01_00"},{"itemTypeId":"$t!-2_ICMSearchv-1","displayName":"ICMSearch","localName":"ICMSearch","queryName":"ICMSearch"},{"itemTypeId":"$t!-2_DEP_008_01_01_00v-1","displayName":"Financieel Verkeer Document","localName":"DEP_008_01_01_00","queryName":"DEP_008_01_01_00"},{"itemTypeId":"$t!-2_DEP_007_03_06_00v-1","displayName":"E-Banking","localName":"DEP_007_03_06_00","queryName":"DEP_007_03_06_00"},{"itemTypeId":"$t!-2_DEP_007_03_05_00v-1","displayName":"DL Bank autorisatie","localName":"DEP_007_03_05_00","queryName":"DEP_007_03_05_00"},{"itemTypeId":"$t!-2_DEP_007_03_04_00v-1","displayName":"DL Bank","localName":"DEP_007_03_04_00","queryName":"DEP_007_03_04_00"},{"itemTypeId":"$t!-2_DEP_007_03_03_00v-1","displayName":"OHRA Bank beleggen","localName":"DEP_007_03_03_00","queryName":"DEP_007_03_03_00"},{"itemTypeId":"$t!-2_DEP_007_03_02_00v-1","displayName":"OHRA Bank autorisatie","localName":"DEP_007_03_02_00","queryName":"DEP_007_03_02_00"},{"itemTypeId":"$t!-2_DEP_007_03_01_00v-1","displayName":"OHRA Bank","localName":"DEP_007_03_01_00","queryName":"DEP_007_03_01_00"},{"itemTypeId":"$t!-2_DEP_007_02_04_00v-1","displayName":"DL Bank Betalingsverkeer Mid Office","localName":"DEP_007_02_04_00","queryName":"DEP_007_02_04_00"},{"itemTypeId":"$t!-2_DEP_007_02_03_00v-1","displayName":"DL Bank Geldverkeer Handtekening","localName":"DEP_007_02_03_00","queryName":"DEP_007_02_03_00"},{"itemTypeId":"$t!-2_DEP_007_02_02_00v-1","displayName":"DL Bank Betalingsverkeer Treasury","localName":"DEP_007_02_02_00","queryName":"DEP_007_02_02_00"},{"itemTypeId":"$t!-2_DEP_007_02_01_00v-1","displayName":"DL Bank Geldverkeer IRS","localName":"DEP_007_02_01_00","queryName":"DEP_007_02_01_00"},{"itemTypeId":"$t!-2_DEP_007_01_01_00v-1","displayName":"DL Bank Maatwerk Krediet Document","localName":"DEP_007_01_01_00","queryName":"DEP_007_01_01_00"},{"itemTypeId":"$t!-2_DEP_007_01_00_00v-1","displayName":"DL Bank Maatwerk Krediet Dossier","localName":"DEP_007_01_00_00","queryName":"DEP_007_01_00_00"},{"itemTypeId":"$t!-2_DEP_005_02_03_00v-1","displayName":"Pensioen BSN Document Medisch","localName":"DEP_005_02_03_00","queryName":"DEP_005_02_03_00"},{"itemTypeId":"$t!-2_DEP_005_02_01_00v-1","displayName":"Pensioen BSN Document Algemeen","localName":"DEP_005_02_01_00","queryName":"DEP_005_02_01_00"},{"itemTypeId":"$t!-2_DEP_005_02_00_00v-1","displayName":"Pensioen BSN dossier","localName":"DEP_005_02_00_00","queryName":"DEP_005_02_00_00"},{"itemTypeId":"$t!-2_DEP_005_01_03_00v-1","displayName":"Pensioen Collectief A Document Medisch","localName":"DEP_005_01_03_00","queryName":"DEP_005_01_03_00"},{"itemTypeId":"$t!-2_DEP_005_01_01_00v-1","displayName":"Pensioen Collectief A Document Algemeen","localName":"DEP_005_01_01_00","queryName":"DEP_005_01_01_00"},{"itemTypeId":"$t!-2_DEP_005_01_00_00v-1","displayName":"Pensioen Collectief A dossier","localName":"DEP_005_01_00_00","queryName":"DEP_005_01_00_00"},{"itemTypeId":"$t!-2_DEP_004_01_01_00v-1","displayName":"Pensioen documenten","localName":"DEP_004_01_01_00","queryName":"DEP_004_01_01_00"},{"itemTypeId":"$t!-2_DEP_004_01_00_00v-1","displayName":"Pensioen dossier","localName":"DEP_004_01_00_00","queryName":"DEP_004_01_00_00"},{"itemTypeId":"$t!-2_DEP_003_01_01_00v-1","displayName":"M&amp;V Intermediair documenten","localName":"DEP_003_01_01_00","queryName":"DEP_003_01_01_00"},{"itemTypeId":"$t!-2_DEP_003_01_00_00v-1","displayName":"M&amp;V Intermediair dossier","localName":"DEP_003_01_00_00","queryName":"DEP_003_01_00_00"},{"itemTypeId":"$t!-2_DEP_002_09_02_00v-1","displayName":"Schade Zakelijk Uitgaande Herverzekering","localName":"DEP_002_09_02_00","queryName":"DEP_002_09_02_00"},{"itemTypeId":"$t!-2_DEP_002_09_01_00v-1","displayName":"Schade Zakelijk Inkomende Herverzekering","localName":"DEP_002_09_01_00","queryName":"DEP_002_09_01_00"},{"itemTypeId":"$t!-2_DEP_002_08_05_00v-1","displayName":"VMC DL Eigen Personeel","localName":"DEP_002_08_05_00","queryName":"DEP_002_08_05_00"},{"itemTypeId":"$t!-2_DEP_002_08_04_00v-1","displayName":"VMC IVB Markt","localName":"DEP_002_08_04_00","queryName":"DEP_002_08_04_00"},{"itemTypeId":"$t!-2_DEP_002_08_03_00v-1","displayName":"IVB Medisch Arnhem","localName":"DEP_002_08_03_00","queryName":"DEP_002_08_03_00"},{"itemTypeId":"$t!-2_DEP_002_08_02_00v-1","displayName":"IVB Relatiebeheer en Services Arnhem","localName":"DEP_002_08_02_00","queryName":"DEP_002_08_02_00"},{"itemTypeId":"$t!-2_DEP_002_08_01_00v-1","displayName":"IVB Claims WIA Arnhem","localName":"DEP_002_08_01_00","queryName":"DEP_002_08_01_00"},{"itemTypeId":"$t!-2_DEP_002_07_03_00v-1","displayName":"PSB Acceptatie en Mutatie NB&amp;D","localName":"DEP_002_07_03_00","queryName":"DEP_002_07_03_00"},{"itemTypeId":"$t!-2_DEP_002_07_02_00v-1","displayName":"PSB Acceptatie en Mutatie OHRA","localName":"DEP_002_07_02_00","queryName":"DEP_002_07_02_00"},{"itemTypeId":"$t!-2_DEP_002_07_01_00v-1","displayName":"PSB Acceptatie en Mutatie DL","localName":"DEP_002_07_01_00","queryName":"DEP_002_07_01_00"},{"itemTypeId":"$t!-2_DEP_002_06_05_00v-1","displayName":"PSB Claims OHRA VIP","localName":"DEP_002_06_05_00","queryName":"DEP_002_06_05_00"},{"itemTypeId":"$t!-2_DEP_002_06_04_00v-1","displayName":"PSB Claims OHRA Medisch","localName":"DEP_002_06_04_00","queryName":"DEP_002_06_04_00"},{"itemTypeId":"$t!-2_DEP_002_06_03_00v-1","displayName":"PSB Claims OHRA Algemeen","localName":"DEP_002_06_03_00","queryName":"DEP_002_06_03_00"},{"itemTypeId":"$t!-2_DEP_002_06_02_00v-1","displayName":"PSB Claims DL Medisch","localName":"DEP_002_06_02_00","queryName":"DEP_002_06_02_00"},{"itemTypeId":"$t!-2_DEP_002_06_01_00v-1","displayName":"PSB Claims DL Algemeen","localName":"DEP_002_06_01_00","queryName":"DEP_002_06_01_00"},{"itemTypeId":"$t!-2_DEP_002_05_01_00v-1","displayName":"DLS NSF Claims Algemeen","localName":"DEP_002_05_01_00","queryName":"DEP_002_05_01_00"},{"itemTypeId":"$t!-2_DEP_002_05_00_00v-1","displayName":"NSF Schade Dossier","localName":"DEP_002_05_00_00","queryName":"DEP_002_05_00_00"},{"itemTypeId":"$t!-2_DEP_002_04_01_00v-1","displayName":"Beurs acceptatie document","localName":"DEP_002_04_01_00","queryName":"DEP_002_04_01_00"},{"itemTypeId":"$t!-2_DEP_002_04_00_00v-1","displayName":"Beurs acceptatie dossier","localName":"DEP_002_04_00_00","queryName":"DEP_002_04_00_00"},{"itemTypeId":"$t!-2_DEP_002_03_02_00v-1","displayName":"Collectiviteit VIP","localName":"DEP_002_03_02_00","queryName":"DEP_002_03_02_00"},{"itemTypeId":"$t!-2_DEP_002_03_01_00v-1","displayName":"Collectiviteit","localName":"DEP_002_03_01_00","queryName":"DEP_002_03_01_00"},{"itemTypeId":"$t!-2_DEP_002_03_00_00v-1","displayName":"Collectiviteitsdossier","localName":"DEP_002_03_00_00","queryName":"DEP_002_03_00_00"},{"itemTypeId":"$t!-2_DEP_002_02_04_00v-1","displayName":"Claims VIP Medisch","localName":"DEP_002_02_04_00","queryName":"DEP_002_02_04_00"},{"itemTypeId":"$t!-2_DEP_002_02_03_00v-1","displayName":"Claims Medisch","localName":"DEP_002_02_03_00","queryName":"DEP_002_02_03_00"},{"itemTypeId":"$t!-2_DEP_002_02_02_00v-1","displayName":"Claims VIP","localName":"DEP_002_02_02_00","queryName":"DEP_002_02_02_00"},{"itemTypeId":"$t!-2_DEP_002_02_01_00v-1","displayName":"Claims Algemeen","localName":"DEP_002_02_01_00","queryName":"DEP_002_02_01_00"},{"itemTypeId":"$t!-2_DEP_002_02_00_00v-1","displayName":"Claimsdossier","localName":"DEP_002_02_00_00","queryName":"DEP_002_02_00_00"},{"itemTypeId":"$t!-2_DEP_002_01_04_00v-1","displayName":"Acceptatie VIP Medisch","localName":"DEP_002_01_04_00","queryName":"DEP_002_01_04_00"},{"itemTypeId":"$t!-2_DEP_002_01_03_00v-1","displayName":"Acceptatie Medisch","localName":"DEP_002_01_03_00","queryName":"DEP_002_01_03_00"},{"itemTypeId":"$t!-2_DEP_002_01_02_00v-1","displayName":"Acceptatie VIP","localName":"DEP_002_01_02_00","queryName":"DEP_002_01_02_00"},{"itemTypeId":"$t!-2_DEP_002_01_01_00v-1","displayName":"Acceptatie Algemeen","localName":"DEP_002_01_01_00","queryName":"DEP_002_01_01_00"},{"itemTypeId":"$t!-2_DEP_002_01_00_00v-1","displayName":"Acceptatiedossier","localName":"DEP_002_01_00_00","queryName":"DEP_002_01_00_00"},{"itemTypeId":"$t!-2_DEP_001_04_04_00v-1","displayName":"DLL MD NSF","localName":"DEP_001_04_04_00","queryName":"DEP_001_04_04_00"},{"itemTypeId":"$t!-2_DEP_001_04_03_00v-1","displayName":"DLL MD OHRA","localName":"DEP_001_04_03_00","queryName":"DEP_001_04_03_00"},{"itemTypeId":"$t!-2_DEP_001_04_02_00v-1","displayName":"DLL MD Collectief","localName":"DEP_001_04_02_00","queryName":"DEP_001_04_02_00"},{"itemTypeId":"$t!-2_DEP_001_04_01_00v-1","displayName":"DLL MD Polis","localName":"DEP_001_04_01_00","queryName":"DEP_001_04_01_00"},{"itemTypeId":"$t!-2_DEP_001_02_01_00v-1","displayName":"Leven Zakelijk Contractniveau","localName":"DEP_001_02_01_00","queryName":"DEP_001_02_01_00"},{"itemTypeId":"$t!-2_DEP_001_02_00_00v-1","displayName":"Leven Zakelijk Deelnemersniveau","localName":"DEP_001_02_00_00","queryName":"DEP_001_02_00_00"},{"itemTypeId":"$t!-2_DEP_001_01_02_00v-1","displayName":"Leven Rekening Courant Nummer","localName":"DEP_001_01_02_00","queryName":"DEP_001_01_02_00"},{"itemTypeId":"$t!-2_DEP_001_01_01_00v-1","displayName":"Leven Polis Particulier","localName":"DEP_001_01_01_00","queryName":"DEP_001_01_01_00"},{"itemTypeId":"$t!-2_DEP_001_01_00_00v-1","displayName":"Polisdossiers Leven Particulier","localName":"DEP_001_01_00_00","queryName":"DEP_001_01_00_00"},{"itemTypeId":"$t!-2_DEP_006_02_03_00v-1","displayName":"AAV Pensioen BSN Document Medisch","localName":"DEP_006_02_03_00","queryName":"DEP_006_02_03_00"},{"itemTypeId":"$t!-2_DEP_006_02_01_00v-1","displayName":"AAV Pensioen BSN Document Algemeen","localName":"DEP_006_02_01_00","queryName":"DEP_006_02_01_00"},{"itemTypeId":"$t!-2_DEP_006_02_00_00v-1","displayName":"AAV Pensioen BSN Dossier","localName":"DEP_006_02_00_00","queryName":"DEP_006_02_00_00"},{"itemTypeId":"$t!-2_DEP_006_01_03_00v-1","displayName":"AAV Pensioen Collectief A Document Medisch","localName":"DEP_006_01_03_00","queryName":"DEP_006_01_03_00"},{"itemTypeId":"$t!-2_DEP_006_01_01_00v-1","displayName":"AAV Pensioen Collectief A Document Algemeen","localName":"DEP_006_01_01_00","queryName":"DEP_006_01_01_00"},{"itemTypeId":"$t!-2_DEP_006_01_00_00v-1","displayName":"AAV Pensioen Collectief A Dossier","localName":"DEP_006_01_00_00","queryName":"DEP_006_01_00_00"},{"itemTypeId":"$t!-2_ICMDRFOLDERSv-1","displayName":"Document Routing Folders","localName":"ICMDRFOLDERS","queryName":"ICMDRFOLDERS"},{"itemTypeId":"$t!-2_NOINDEXv-1","displayName":"NOINDEX","localName":"NOINDEX","queryName":"NOINDEX"},{"itemTypeId":"$t!-2_DEP_006_10_02_00v-1","displayName":"AAV Finance 2","localName":"DEP_006_10_02_00","queryName":"DEP_006_10_02_00"},{"itemTypeId":"$t!-2_DEP_006_10_01_00v-1","displayName":"AAV Finance 1","localName":"DEP_006_10_01_00","queryName":"DEP_006_10_01_00"},{"itemTypeId":"$t!-2_DEP_002_08_07_00v-1","displayName":"Schade Medisch Personeel Ongevallen","localName":"DEP_002_08_07_00","queryName":"DEP_002_08_07_00"},{"itemTypeId":"$t!-2_DEP_002_08_06_00v-1","displayName":"Schade Medisch Letsel","localName":"DEP_002_08_06_00","queryName":"DEP_002_08_06_00"},{"itemTypeId":"$t!-2_DEP_001_05_02_00v-1","displayName":"DL Leven NSF","localName":"DEP_001_05_02_00","queryName":"DEP_001_05_02_00"},{"itemTypeId":"$t!-2_DEP_001_05_01_00v-1","displayName":"DL Leven OHRA","localName":"DEP_001_05_01_00","queryName":"DEP_001_05_01_00"},{"itemTypeId":"$t!-2_DEP_002_02_01_99v-1","displayName":"Claims Algemeen Testitemtype","localName":"DEP_002_02_01_99","queryName":"DEP_002_02_01_99"},{"itemTypeId":"$t!-2_TEST_B_TARGET_ITEMTYPEv-1","displayName":"TEST_B_TARGET_ITEMTYPE","localName":"TEST_B_TARGET_ITEMTYPE","queryName":"TEST_B_TARGET_ITEMTYPE"},{"itemTypeId":"$t!-2_TEST_A_SOURCE_ITEMTYPEv-1","displayName":"TEST_A_SOURCE_ITEMTYPE","localName":"TEST_A_SOURCE_ITEMTYPE","queryName":"TEST_A_SOURCE_ITEMTYPE"},{"itemTypeId":"$t!-2_DEP_011_01_01_00v-1","displayName":"DDCCS Tijdelijke Opslag","localName":"DEP_011_01_01_00","queryName":"DEP_011_01_01_00"},{"itemTypeId":"$t!-2_Test_CMIS_namev-1","displayName":"Test_CMIS_name","localName":"Test_CMIS_name","queryName":"Test_CMIS_name"},{"itemTypeId":"$t!-2_DEP_001_09_03_99v-1","displayName":"DDCIS Cache Clear Testitemtype","localName":"DEP_001_09_03_99","queryName":"DEP_001_09_03_99"},{"itemTypeId":"$t!-2_DEP_001_09_02_00v-1","displayName":"DDCIS AAT","localName":"DEP_001_09_02_00","queryName":"DEP_001_09_02_00"},{"itemTypeId":"$t!-2_DEP_001_09_01_00v-1","displayName":"CIS tijdelijke opslag mail","localName":"DEP_001_09_01_00","queryName":"DEP_001_09_01_00"},{"itemTypeId":"$t!-2_DEP_002_00_00_00v-1","displayName":"Performancetest","localName":"DEP_002_00_00_00","queryName":"DEP_002_00_00_00"},{"itemTypeId":"$t!-2_DEP_006_02_05_00v-1","displayName":"AAV Z-Pensioenadvies","localName":"DEP_006_02_05_00","queryName":"DEP_006_02_05_00"},{"itemTypeId":"$t!-2_DEP_006_02_04_00v-1","displayName":"AAV Pensioenadvies","localName":"DEP_006_02_04_00","queryName":"DEP_006_02_04_00"},{"itemTypeId":"$t!-2_AAV_Testv-1","displayName":"AAV_Test_1","localName":"AAV_Test","queryName":"AAV_Test"},{"itemTypeId":"$t!-2_DEP_010_01_03_00v-1","displayName":"Asset Management Treasury","localName":"DEP_010_01_03_00","queryName":"DEP_010_01_03_00"},{"itemTypeId":"$t!-2_Test_T_omgevingv-1","displayName":"Test_T_omgeving - decimal bug","localName":"Test_T_omgeving","queryName":"Test_T_omgeving"},{"itemTypeId":"$t!-2_DEP_010_01_02_00v-1","displayName":"Niet in gebruik - Asset Management Treasury","localName":"DEP_010_01_02_00","queryName":"DEP_010_01_02_00"},{"itemTypeId":"$t!-2_DEP_010_01_01_00v-1","displayName":"Asset Management Facturen","localName":"DEP_010_01_01_00","queryName":"DEP_010_01_01_00"},{"itemTypeId":"$t!-2_DEP_002_02_05_00v-1","displayName":"Claims AOV/ONG","localName":"DEP_002_02_05_00","queryName":"DEP_002_02_05_00"},{"itemTypeId":"$t!-2_DEP_TEST_DOCHTER_COMPv-1","displayName":"DEP_TEST_DOCHTER_COMP","localName":"DEP_TEST_DOCHTER_COMP","queryName":"DEP_TEST_DOCHTER_COMP"},{"itemTypeId":"$t!-2_DEP_002_09_03_00v-1","displayName":"Schade Zakelijk Groepsverzekering","localName":"DEP_002_09_03_00","queryName":"DEP_002_09_03_00"}]'
			>
				<forward name="success" path="OK" />
			</pipe>

		</pipeline>
	</adapter>
</ibis>
